tlviz/__init__.py
tlviz/_module_utils.py
tlviz/_tl_utils.py
tlviz/_xarray_wrapper.py
tlviz/conftest.py
tlviz/data.py
tlviz/factor_tools.py
tlviz/model_evaluation.py
tlviz/multimodel_evaluation.py
tlviz/outliers.py
tlviz/postprocessing.py
tlviz/utils.py
tlviz/visualisation.py
tlviz/datasets/oslo_bike.nc4
tensorly_viz-0.1.7.dist-info/LICENSE
tensorly_viz-0.1.7.dist-info/METADATA
tensorly_viz-0.1.7.dist-info/WHEEL
tensorly_viz-0.1.7.dist-info/top_level.txt
tensorly_viz-0.1.7.dist-info/RECORD
