Metadata-Version: 2.1
Name: tensorly-viz
Version: 0.1.7
Summary: Package to visualise component-based decomposition models such as PCA and PARAFAC
Home-page: https://tensorly.org/viz
Author: Marie Roald & Yngve Mardal Moe
Author-email: roald.marie@gmail.com
License: "MIT license",
Platform: UNKNOWN
Classifier: Intended Audience :: Developers
Classifier: License :: OSI Approved :: MIT License
Classifier: Natural Language :: English
Classifier: Programming Language :: Python :: 3.8
Classifier: Programming Language :: Python :: 3.9
Requires-Dist: numpy
Requires-Dist: scipy
Requires-Dist: matplotlib
Requires-Dist: pandas (>=1.1.0)
Requires-Dist: statsmodels
Requires-Dist: xarray
Requires-Dist: requests
Provides-Extra: all
Requires-Dist: pingouin ; extra == 'all'
Provides-Extra: devel
Requires-Dist: flake8 ; extra == 'devel'
Requires-Dist: isort ; extra == 'devel'
Requires-Dist: black ; extra == 'devel'
Requires-Dist: bump2version ; extra == 'devel'
Provides-Extra: docs
Requires-Dist: sphinx ; extra == 'docs'
Requires-Dist: sphinx-gallery ; extra == 'docs'
Requires-Dist: sphinxcontrib-bibtex ; extra == 'docs'
Requires-Dist: autodocsumm ; extra == 'docs'
Requires-Dist: numpydoc ; extra == 'docs'
Requires-Dist: tensorly ; extra == 'docs'
Requires-Dist: tensorly-sphinx-theme ; extra == 'docs'
Requires-Dist: plotly (>=4.12) ; extra == 'docs'
Requires-Dist: torch ; extra == 'docs'
Provides-Extra: test
Requires-Dist: pytest ; extra == 'test'
Requires-Dist: pytest-randomly ; extra == 'test'
Requires-Dist: pytest-cov ; extra == 'test'
Requires-Dist: coverage ; extra == 'test'
Requires-Dist: tensorly ; extra == 'test'
Requires-Dist: plotly (>=4.12) ; extra == 'test'
Requires-Dist: torch ; extra == 'test'
